teaching_tools/ab_test/data.py
teaching_tools/ab_test/data_model.py
teaching_tools/ab_test/experiment.py
teaching_tools/ab_test/params.py
teaching_tools/ab_test/repository.py
teaching_tools/ab_test/reset.py
teaching_tools/widgets.py
teaching_tools-0.11.0.dist-info/WHEEL
teaching_tools-0.11.0.dist-info/METADATA
teaching_tools-0.11.0.dist-info/RECORD
