Metadata-Version: 2.1
Name: teaching-tools
Version: 0.11.0
Summary: Teaching tools for the WQU Data Science Lab
Author: Nicholas Cifuentes-Goodbody
Requires-Python: >=3.8,<4.0
Classifier: Programming Language :: Python :: 3
Classifier: Programming Language :: Python :: 3.8
Classifier: Programming Language :: Python :: 3.9
Classifier: Programming Language :: Python :: 3.10
Requires-Dist: ipython (>=8.1.1,<9.0.0)
Requires-Dist: ipywidgets (>=7.6.5,<8.0.0)
Requires-Dist: matplotlib (>=3.4.3,<4.0.0)
Requires-Dist: names (>=0.3.0,<0.4.0)
Requires-Dist: numpy (>=1.21,<2.0)
Requires-Dist: pandas (>=1.4.1,<2.0.0)
Requires-Dist: pymongo (>=4.1.1,<5.0.0)
Requires-Dist: randomtimestamp (>=2.2,<3.0)
Requires-Dist: sklearn (>=0.0,<0.1)
